files_com_mcp/__init__.py
files_com_mcp/__main__.py
files_com_mcp/server.py
files_com_mcp/utils.py
files_com_mcp/authored_tools/__init__.py
files_com_mcp/authored_tools/check_platform_status.py
files_com_mcp/authored_tools/debug.py
files_com_mcp/authored_tools/local_transfer.py
files_com_mcp/generated_tools/__init__.py
files_com_mcp/generated_tools/automation.py
files_com_mcp/generated_tools/bundle.py
files_com_mcp/generated_tools/bundle_download.py
files_com_mcp/generated_tools/bundle_notification.py
files_com_mcp/generated_tools/bundle_recipient.py
files_com_mcp/generated_tools/bundle_registration.py
files_com_mcp/generated_tools/file.py
files_com_mcp/generated_tools/folder.py
files_com_mcp/generated_tools/group.py
files_com_mcp/generated_tools/history.py
files_com_mcp/generated_tools/permission.py
files_com_mcp/generated_tools/remote_server.py
files_com_mcp/generated_tools/user.py
files_com_mcp/patches/__init__.py
files_com_mcp/patches/fastmcp_settings_patch.py
files_com_mcp/patches/python_sdk_patch.py
files_com_mcp-1.0.40.dist-info/licenses/LICENSE
files_com_mcp-1.0.40.dist-info/METADATA
files_com_mcp-1.0.40.dist-info/WHEEL
files_com_mcp-1.0.40.dist-info/entry_points.txt
files_com_mcp-1.0.40.dist-info/top_level.txt
files_com_mcp-1.0.40.dist-info/RECORD
