Metadata-Version: 2.4
Name: files_com_mcp
Version: 1.0.40
Summary: MCP for the Files.com API
License: MIT
Requires-Python: >=3.10
License-File: LICENSE
Requires-Dist: fastmcp==2.12.4
Requires-Dist: files-com
Dynamic: license-file
